{
  "current_model_name": "_LSTM_all_features",
  "model_type": "Mix_Bid_PeepHole_LSTM_Dense_ANN",
  "regularizers_l1_l2": "True",
  "l1": 0.001,
  "l2": 0.001,
  "units_layer_1": 1,
  "activation_1": "softsign",
  "return_sequences_layer_1": "True",
  "time_steps_days": 28,
  "features": "calculation in code",
  "dropout_layer_1": 0.125,
  "units_layer_2": 1,
  "activation_2": "softsign",
  "return_sequences_layer_2": "True",
  "dropout_layer_2": 0.125,
  "units_layer_3": 1,
  "activation_3": "softsign",
  "return_sequences_layer_3": "True",
  "dropout_layer_3": 0.125,
  "units_layer_4": 1,
  "activation_4": "softsign",
  "return_sequences_layer_4": "False",
  "dropout_layer_4": 0.125,
  "units_final_layer": "nof_features",
  "activation_final_layer": "None",
  "repeat_vector": 28,
  "optimizer": "adam",
  "learning_rate": 0.000175,
  "loss_1": "mse",
  "loss_2": "None",
  "loss_3": "None",
  "metrics1": "mse",
  "metrics2": "None",
  "epochs": 5000,
  "batch_size": 8,
  "early_stopping_patience": 7,
  "workers": 6,
  "stride_window_walk": 7,
  "days_in_focus_frame": 84
}