{
  "current_model_name": "_LSTM_all_features",
  "model_type": "PeepHole_Encode_Decode",
  "regularizers_l1_l2": "True",
  "l1": 0.001,
  "l2": 0.001,
  "units_layer_1": 48,
  "activation_1": "tanh",
  "return_sequences_layer_1": "True",
  "time_steps_days": 56,
  "features": "aggregated_by_group",
  "dropout_layer_1": 0.0,
  "units_layer_2": 1,
  "activation_2": "tanh",
  "return_sequences_layer_2": "True",
  "dropout_layer_2": 0.1,
  "units_layer_3": 96,
  "activation_3": "softsign",
  "return_sequences_layer_3": "True",
  "dropout_layer_3": 0.0,
  "units_layer_4": 48,
  "activation_4": "softsign",
  "return_sequences_layer_4": "False",
  "dropout_layer_4": 0.125,
  "units_final_layer": 1,
  "activation_final_layer": "None",
  "repeat_vector": 28,
  "optimizer": "sgd",
  "learning_rate": 0.000175,
  "loss_1": "m_mape",
  "loss_2": "None",
  "loss_3": "None",
  "metrics1": "mse",
  "metrics2": "None",
  "epochs": 500,
  "batch_size": 16,
  "early_stopping_patience": 7,
  "workers": 6,
  "stride_window_walk": 1,
  "days_in_focus_frame": 84
}